{
  "parent": "tconstruct:item/plate_shield",
  "display": {
    "thirdperson_righthand": {
      "rotation": [
        45,
        135,
        0
      ],
      "translation": [
        3.6,
        -3,
        -2
      ],
      "scale": [
        1,
        1,
        1
      ]
    },
    "thirdperson_lefthand": {
      "rotation": [
        45,
        315,
        0
      ],
      "translation": [
        3.6,
        -3,
        -2
      ],
      "scale": [
        1,
        1,
        1
      ]
    },
    "firstperson_righthand": {
      "rotation": [
        0,
        0,
        5
      ],
      "translation": [
        -5,
        -5,
        -0.2
      ],
      "scale": [
        1,
        1,
        1
      ]
    },
    "firstperson_lefthand": {
      "rotation": [
        0,
        0,
        5
      ],
      "translation": [
        -5,
        -5,
        -0.2
      ],
      "scale": [
        1,
        1,
        1
      ]
    }
  }
}